MANIFEST.in
__version__
setup.cfg
setup.py
sempylver/__init__.py
sempylver/__main__.py
sempylver/actions.py
sempylver/commit-msg
sempylver/commit_msg.py
sempylver/constants.py
sempylver/global_config.yml
sempylver/post-commit
sempylver/post_commit.py
sempylver/setup
sempylver/utils.py
sempylver.egg-info/PKG-INFO
sempylver.egg-info/SOURCES.txt
sempylver.egg-info/dependency_links.txt
sempylver.egg-info/entry_points.txt
sempylver.egg-info/requires.txt
sempylver.egg-info/top_level.txt