Metadata-Version: 1.1
Name: sempylver
Version: 1.4.3
Summary: A simple tool for tracking the semantic version of projects
Home-page: https://github.com/jeffrey-cochran/sempylver
Author: Jeff Cochran
Author-email: jeffrey.david.cochran@gmail.com
License: UNKNOWN
Download-URL: https://github.com/jeffrey-cochran/sempylver/archive/1.4.3.tar.gz
Keywords: versioning,semantic,cli,version,control
Platform: UNKNOWN
